auth_mcp_stdio.py
teamcenter_mcp_server_test-0.1.6.dist-info/METADATA
teamcenter_mcp_server_test-0.1.6.dist-info/WHEEL
teamcenter_mcp_server_test-0.1.6.dist-info/entry_points.txt
teamcenter_mcp_server_test-0.1.6.dist-info/top_level.txt
teamcenter_mcp_server_test-0.1.6.dist-info/RECORD
