Metadata-Version: 2.4
Name: teamcenter-mcp-server-test
Version: 0.1.6
Summary: Authenticated MCP server for Teamcenter Knowledge Base APIs with Azure AD support
Requires-Python: >=3.10
Requires-Dist: fastapi>=0.104.1
Requires-Dist: uvicorn>=0.24.0
Requires-Dist: fastmcp>=0.1.0
Requires-Dist: httpx>=0.24.0
Requires-Dist: requests>=2.28.0
Provides-Extra: dev
Requires-Dist: pytest>=7.0.0; extra == "dev"
Requires-Dist: pytest-asyncio>=0.21.0; extra == "dev"
